pygifmaker/__init__.py
pygifmaker/gifmaker.py
pygifmaker-1.0.1.dist-info/LICENSE
pygifmaker-1.0.1.dist-info/METADATA
pygifmaker-1.0.1.dist-info/WHEEL
pygifmaker-1.0.1.dist-info/top_level.txt
pygifmaker-1.0.1.dist-info/RECORD
