Metadata-Version: 2.1
Name: pygifmaker
Version: 1.0.1
Summary: Test package for distribution
Home-page: UNKNOWN
Author: Eunki7
Author-email: outsider7224@gmail.com
License: UNKNOWN
Keywords: GIFMaker,gifmaker
Platform: UNKNOWN
Classifier: Programming Language :: Python :: 3
Classifier: License :: OSI Approved :: MIT License
Classifier: Operating System :: OS Independent
Requires-Python: >=3
License-File: LICENSE
Requires-Dist: pillow
